LICENSE
README.md
setup.cfg
setup.py
flake8_intsights/__init__.py
flake8_intsights/checker.py
flake8_intsights.egg-info/PKG-INFO
flake8_intsights.egg-info/SOURCES.txt
flake8_intsights.egg-info/dependency_links.txt
flake8_intsights.egg-info/entry_points.txt
flake8_intsights.egg-info/not-zip-safe
flake8_intsights.egg-info/requires.txt
flake8_intsights.egg-info/top_level.txt
flake8_intsights/checkers/__init__.py
flake8_intsights/checkers/_checker.py
flake8_intsights/checkers/_errors.py
flake8_intsights/checkers/backslashes.py
flake8_intsights/checkers/blank_lines.py
flake8_intsights/checkers/builtins.py
flake8_intsights/checkers/comments.py
flake8_intsights/checkers/debugging.py
flake8_intsights/checkers/declerations.py
flake8_intsights/checkers/duplications.py
flake8_intsights/checkers/imports.py
flake8_intsights/checkers/indents.py
flake8_intsights/checkers/mutables.py
flake8_intsights/checkers/naming.py
flake8_intsights/checkers/raise_exception.py
flake8_intsights/checkers/single_quotes.py
flake8_intsights/checkers/spacing.py
flake8_intsights/checkers/string_interpolation.py
tests/test_backslashes.py
tests/test_blank_lines.py
tests/test_builtins.py
tests/test_checker.py
tests/test_comments.py
tests/test_debugging.py
tests/test_declerations.py
tests/test_duplications.py
tests/test_imports.py
tests/test_indents.py
tests/test_mutables.py
tests/test_naming.py
tests/test_raise_exception.py
tests/test_single_quotes.py
tests/test_spacing.py
tests/test_string_interpolation.py