Metadata-Version: 2.1
Name: flake8-intsights
Version: 0.3.1
Summary: Uncompromising and opinionated flake8 plugin which follows Intsights' practices
Home-page: https://github.com/Intsights/flake8-intsights
Author: Gal Ben David
Author-email: gal@intsights.com
License: MIT
Project-URL: Source, https://github.com/Intsights/flake8-intsights
Keywords: flake8 conventions style lint linter intsights
Classifier: License :: OSI Approved :: MIT License
Classifier: Programming Language :: Python :: 3.7
Classifier: Programming Language :: Python :: 3.8
Classifier: Programming Language :: Python :: 3.9
Classifier: Programming Language :: Python :: 3.10
Classifier: Programming Language :: Python :: 3.11
Requires-Python: >=3.7
License-File: LICENSE
Requires-Dist: astroid==2.15.8
Requires-Dist: flake8
Requires-Dist: flake8-assertive
Requires-Dist: flake8-comprehensions
